{
    "name": "Galack Colada",
    "description": "Drink inspired by nestle white chocolate",
    "github": "Kouthk",
    "ingredients": [
        {
            "quantity": "1 or more",
            "measure": "Cup",
            "ingredient": "Ice cubes"
        },
        {
            "quantity": "1",
            "measure": "little bottle",
            "ingredient": "Galack"
        },
        {
            "quantity": "3",
            "measure": "Tablespoon",
            "ingredient": "Pineapple juice"
        },
        {
            "quantity": "2",
            "measure": "Tablespoon",
            "ingredient": "Rum"
        },
        {
            "quantity": "1",
            "measure": "Tablespoon",
            "ingredient": "Coconut milk"
        },
        {
            "quantity": "1",
            "measure": "Tablespoon",
            "ingredient": "Malibu"
        },
        {
            "quantity": "1",
            "measure": "Tablespoon",
            "ingredient": "sweetened condensed milk"
        }
       
    ],
    "directions": [
        "put it all in a blender.",
        "Blend until smooth.",
        "In a glass of 500ml Pass condensed milk on edge",
        "Pineapple Triangle on the Edge Cherry on the edge White chocolate bar in the glass"
    ],
    "image": "galack-colada.jpg",
    "keywords": [
        "galack",
        "pineapple juice",
        "alcoholic",
        "rum",
        "Malibu"
    ]
}
